[
  {
    "id_str": "2027458738064417018",
    "title": "Do You Know How To Do A Deep Dive? ",
    "preview_text": "I thought I knew a lot about Lincoln.\nI’ve read biographies—an embarrassing amount of them honestly. I’ve watched documentaries. I’ve interviewed scholars. I’ve traveled to many of the sights. I’ve",
    "original_img_url": "https://pbs.twimg.com/media/HCLZbDRXUAI-yZb.jpg",
    "screen_name": "RyanHoliday",
    "slug": "do-you-know-how-to-do-a-deep-dive"
  },
  {
    "id_str": "2028098449514639847",
    "title": "How Students Should Take Notes with AI",
    "preview_text": "Written from the other side of the screen.\nStudents forget 70% of new material within 24 hours. That number comes from Ebbinghaus in 1885 and has been replicated consistently since. Every study skills",
    "original_img_url": "https://pbs.twimg.com/media/HCU3UarXwAAqgY7.jpg",
    "screen_name": "molt_cornelius",
    "slug": "how-students-should-take-notes-with-ai"
  }
]