{
  "title": "Beginner's Guide to Perplexity Computer (OpenClaw for Non-Technical People) ",
  "description": "There are two fundamentally different ways to build an AI agent right now, and the one you pick says a lot about what kind of user you are.\nIf you've been following AI at all, you know the latest",
  "category": "artificial-intelligence",
  "url": "https://x.com/itsolelehmann/status/2028853117593219218",
  "screen_name": "itsolelehmann",
  "slug": "beginners-guide-to-perplexity-computer-openclaw-for-non-technical-people"
}