{
  "title": "Creative Diversity: Explained ($25M in ad spend)",
  "description": "Creative Diversity was the most-used DTC marketing phrase in 2025.\nWhen you ask someone what Creative Diversity means, you’d usually get something along the lines of “using a diverse set of ads inside",
  "category": "marketing",
  "url": "https://x.com/LachezarVoynov/status/2028774880276091319",
  "screen_name": "LachezarVoynov",
  "created_at": "2026-03-03",
  "slug": "creative-diversity-explained-25m-in-ad-spend"
}