{
  "title": "\"Does This Matter?\" Data Overload, Signal/Noise Ratio & Mental Masturbation",
  "description": "\"People always forget that 50% of a stock’s move in the overall market, 30% is the industry group, and then maybe 20% is the extra alpha from stock picking. And stock picking is full of macro bets.",
  "category": "investing",
  "url": "https://x.com/gregoryblotnick/status/2008915433869480356",
  "screen_name": "gregoryblotnick",
  "created_at": "2026-01-07",
  "slug": "does-this-matter-data-overload-signalnoise-ratio-mental-masturbation"
}