{
  "title": "Dr. Qiang “Al” Zhang - Chairman & Co-CEO, United Imaging Healthcare ",
  "description": "Dr. Qiang “Al” Zhang is one of the co-founders and Chairman & Co-CEO of Shanghai United Imaging Healthcare. Dr. Zhang holds a Ph.D. in Biomedical Engineering from Case Western Reserve University in",
  "category": "entrepreneurship",
  "url": "https://x.com/HospitalsMag/status/2026197975567843804",
  "screen_name": "HospitalsMag",
  "slug": "dr-qiang-al-zhang-chairman-co-ceo-united-imaging-healthcare"
}