{
  "title": "How To Get Ahead of 99% of People (This will reprogram your mind) ",
  "description": "This one skill nobody talks about took me from working at a paper shredding factory to a $300M company.\nIf you want to build a business that prints profits, runs without you needing to work 24 hours a",
  "category": "personal-development",
  "url": "https://x.com/realbrianmoran/status/2026045907595342330",
  "screen_name": "realbrianmoran",
  "slug": "how-to-get-ahead-of-99-of-people-this-will-reprogram-your-mind"
}