{
  "title": "stop being a content creator,       start being a conversion architect",
  "description": "your job isn't to entertain—it's to move people from problem-aware to purchase-ready using systematic psychology\nand most of you are failing at faceless pages because you fundamentally misunderstand",
  "category": "marketing",
  "url": "https://x.com/fromzerotomill/status/2025786165354434812",
  "screen_name": "fromzerotomill",
  "created_at": "2026-02-23",
  "slug": "stop-being-a-content-creator-start-being-a-conversion-architect"
}