{
  "title": "The 8 Professionals You Need to Never Work Again ",
  "description": "Most people make money the same way for their entire lives.\nThey earn it.\nThey get taxed on it.\nThey spend what's left.\nThen they repeat the process.\nEarn → Tax → Spend → Tax → Repeat.\nIt feels",
  "category": "unknown",
  "url": "https://x.com/termsheetinator/status/2029593122062401675",
  "screen_name": "termsheetinator",
  "created_at": "2026-03-05",
  "slug": "the-8-professionals-you-need-to-never-work-again"
}