{
  "title": "THE KEY TO WIN IN LIFE (ACT II)                 MASTERY",
  "description": "Act I gave you time.\nBut time alone is not enough.\nLongevity without mastery is empty.\nA strong body and a sharp mind mean nothing\nif they are not governed by discipline, purpose, and self-command.",
  "category": "personal-finance",
  "url": "https://x.com/Nemanja_I_IV/status/2022042779803861161",
  "screen_name": "Nemanja_I_IV",
  "created_at": "2026-02-12",
  "slug": "the-key-to-win-in-life-act-ii-mastery"
}