{
  "title": "Vitamin C is far more important than you might think and you're probably not consuming enough of it.",
  "description": "It’s George.\nVitamin C is often praised during the winter months due to the effects that it has on the immune system, but this doesn’t even begin to scratch the surface when it comes to how important",
  "category": "health",
  "url": "https://x.com/Helios_Movement/status/2028541874466705547",
  "screen_name": "Helios_Movement",
  "slug": "vitamin-c-is-far-more-important-than-you-might-think-and-youre-probably-not-consuming-enough-of-it"
}